<?xml version="1.0" encoding="utf-8" ?>
<tree-map>
  <no-comparator/>
  <entry>
    <int>1605</int>
    <fire.pb.map.SWorldMapConfig>
      <id>1605</id>
      <maptype>2</maptype>
      <LevelLimitMin>-1</LevelLimitMin>
      <LevelLimitMax>-1</LevelLimitMax>
      <SubUnderGroundMap>0</SubUnderGroundMap>
      <topx>47</topx>
      <topy>38</topy>
      <bottomx>49</bottomx>
      <bottomy>40</bottomy>
    </fire.pb.map.SWorldMapConfig>
  </entry>
  <entry>
    <int>1606</int>
    <fire.pb.map.SWorldMapConfig>
      <id>1606</id>
      <maptype>2</maptype>
      <LevelLimitMin>-1</LevelLimitMin>
      <LevelLimitMax>-1</LevelLimitMax>
      <SubUnderGroundMap>0</SubUnderGroundMap>
      <topx>71</topx>
      <topy>72</topy>
      <bottomx>73</bottomx>
      <bottomy>74</bottomy>
    </fire.pb.map.SWorldMapConfig>
  </entry>
  <entry>
    <int>1607</int>
    <fire.pb.map.SWorldMapConfig>
      <id>1607</id>
      <maptype>2</maptype>
      <LevelLimitMin>-1</LevelLimitMin>
      <LevelLimitMax>-1</LevelLimitMax>
      <SubUnderGroundMap>0</SubUnderGroundMap>
      <topx>30</topx>
      <topy>70</topy>
      <bottomx>32</bottomx>
      <bottomy>72</bottomy>
    </fire.pb.map.SWorldMapConfig>
  </entry>
  <entry>
    <int>1608</int>
    <fire.pb.map.SWorldMapConfig>
      <id>1608</id>
      <maptype>2</maptype>
      <LevelLimitMin>-1</LevelLimitMin>
      <LevelLimitMax>-1</LevelLimitMax>
      <SubUnderGroundMap>0</SubUnderGroundMap>
      <topx>13</topx>
      <topy>18</topy>
      <bottomx>15</bottomx>
      <bottomy>20</bottomy>
    </fire.pb.map.SWorldMapConfig>
  </entry>
  <entry>
    <int>1609</int>
    <fire.pb.map.SWorldMapConfig>
      <id>1609</id>
      <maptype>2</maptype>
      <LevelLimitMin>-1</LevelLimitMin>
      <LevelLimitMax>-1</LevelLimitMax>
      <SubUnderGroundMap>0</SubUnderGroundMap>
      <topx>57</topx>
      <topy>64</topy>
      <bottomx>59</bottomx>
      <bottomy>66</bottomy>
    </fire.pb.map.SWorldMapConfig>
  </entry>
  <entry>
    <int>1610</int>
    <fire.pb.map.SWorldMapConfig>
      <id>1610</id>
      <maptype>2</maptype>
      <LevelLimitMin>-1</LevelLimitMin>
      <LevelLimitMax>-1</LevelLimitMax>
      <SubUnderGroundMap>0</SubUnderGroundMap>
      <topx>77</topx>
      <topy>63</topy>
      <bottomx>79</bottomx>
      <bottomy>65</bottomy>
    </fire.pb.map.SWorldMapConfig>
  </entry>
  <entry>
    <int>1611</int>
    <fire.pb.map.SWorldMapConfig>
      <id>1611</id>
      <maptype>2</maptype>
      <LevelLimitMin>-1</LevelLimitMin>
      <LevelLimitMax>-1</LevelLimitMax>
      <SubUnderGroundMap>0</SubUnderGroundMap>
      <topx>103</topx>
      <topy>45</topy>
      <bottomx>105</bottomx>
      <bottomy>47</bottomy>
    </fire.pb.map.SWorldMapConfig>
  </entry>
  <entry>
    <int>1612</int>
    <fire.pb.map.SWorldMapConfig>
      <id>1612</id>
      <maptype>2</maptype>
      <LevelLimitMin>-1</LevelLimitMin>
      <LevelLimitMax>-1</LevelLimitMax>
      <SubUnderGroundMap>0</SubUnderGroundMap>
      <topx>22</topx>
      <topy>153</topy>
      <bottomx>24</bottomx>
      <bottomy>155</bottomy>
    </fire.pb.map.SWorldMapConfig>
  </entry>
  <entry>
    <int>1613</int>
    <fire.pb.map.SWorldMapConfig>
      <id>1613</id>
      <maptype>2</maptype>
      <LevelLimitMin>-1</LevelLimitMin>
      <LevelLimitMax>-1</LevelLimitMax>
      <SubUnderGroundMap>0</SubUnderGroundMap>
      <topx>40</topx>
      <topy>29</topy>
      <bottomx>42</bottomx>
      <bottomy>31</bottomy>
    </fire.pb.map.SWorldMapConfig>
  </entry>
  <entry>
    <int>1614</int>
    <fire.pb.map.SWorldMapConfig>
      <id>1614</id>
      <maptype>2</maptype>
      <LevelLimitMin>-1</LevelLimitMin>
      <LevelLimitMax>-1</LevelLimitMax>
      <SubUnderGroundMap>0</SubUnderGroundMap>
      <topx>65</topx>
      <topy>61</topy>
      <bottomx>67</bottomx>
      <bottomy>63</bottomy>
    </fire.pb.map.SWorldMapConfig>
  </entry>
  <entry>
    <int>1615</int>
    <fire.pb.map.SWorldMapConfig>
      <id>1615</id>
      <maptype>2</maptype>
      <LevelLimitMin>-1</LevelLimitMin>
      <LevelLimitMax>-1</LevelLimitMax>
      <SubUnderGroundMap>0</SubUnderGroundMap>
      <topx>107</topx>
      <topy>110</topy>
      <bottomx>109</bottomx>
      <bottomy>112</bottomy>
    </fire.pb.map.SWorldMapConfig>
  </entry>
  <entry>
    <int>1616</int>
    <fire.pb.map.SWorldMapConfig>
      <id>1616</id>
      <maptype>2</maptype>
      <LevelLimitMin>-1</LevelLimitMin>
      <LevelLimitMax>-1</LevelLimitMax>
      <SubUnderGroundMap>0</SubUnderGroundMap>
      <topx>100</topx>
      <topy>38</topy>
      <bottomx>102</bottomx>
      <bottomy>40</bottomy>
    </fire.pb.map.SWorldMapConfig>
  </entry>
  <entry>
    <int>1617</int>
    <fire.pb.map.SWorldMapConfig>
      <id>1617</id>
      <maptype>2</maptype>
      <LevelLimitMin>-1</LevelLimitMin>
      <LevelLimitMax>-1</LevelLimitMax>
      <SubUnderGroundMap>0</SubUnderGroundMap>
      <topx>35</topx>
      <topy>40</topy>
      <bottomx>37</bottomx>
      <bottomy>42</bottomy>
    </fire.pb.map.SWorldMapConfig>
  </entry>
  <entry>
    <int>1618</int>
    <fire.pb.map.SWorldMapConfig>
      <id>1618</id>
      <maptype>2</maptype>
      <LevelLimitMin>-1</LevelLimitMin>
      <LevelLimitMax>-1</LevelLimitMax>
      <SubUnderGroundMap>0</SubUnderGroundMap>
      <topx>45</topx>
      <topy>54</topy>
      <bottomx>47</bottomx>
      <bottomy>56</bottomy>
    </fire.pb.map.SWorldMapConfig>
  </entry>
  <entry>
    <int>1619</int>
    <fire.pb.map.SWorldMapConfig>
      <id>1619</id>
      <maptype>2</maptype>
      <LevelLimitMin>-1</LevelLimitMin>
      <LevelLimitMax>-1</LevelLimitMax>
      <SubUnderGroundMap>0</SubUnderGroundMap>
      <topx>71</topx>
      <topy>88</topy>
      <bottomx>73</bottomx>
      <bottomy>90</bottomy>
    </fire.pb.map.SWorldMapConfig>
  </entry>
  <entry>
    <int>1620</int>
    <fire.pb.map.SWorldMapConfig>
      <id>1620</id>
      <maptype>2</maptype>
      <LevelLimitMin>-1</LevelLimitMin>
      <LevelLimitMax>-1</LevelLimitMax>
      <SubUnderGroundMap>0</SubUnderGroundMap>
      <topx>40</topx>
      <topy>97</topy>
      <bottomx>42</bottomx>
      <bottomy>99</bottomy>
    </fire.pb.map.SWorldMapConfig>
  </entry>
  <entry>
    <int>1621</int>
    <fire.pb.map.SWorldMapConfig>
      <id>1621</id>
      <maptype>2</maptype>
      <LevelLimitMin>-1</LevelLimitMin>
      <LevelLimitMax>-1</LevelLimitMax>
      <SubUnderGroundMap>0</SubUnderGroundMap>
      <topx>83</topx>
      <topy>92</topy>
      <bottomx>85</bottomx>
      <bottomy>94</bottomy>
    </fire.pb.map.SWorldMapConfig>
  </entry>
  <entry>
    <int>1622</int>
    <fire.pb.map.SWorldMapConfig>
      <id>1622</id>
      <maptype>2</maptype>
      <LevelLimitMin>-1</LevelLimitMin>
      <LevelLimitMax>-1</LevelLimitMax>
      <SubUnderGroundMap>0</SubUnderGroundMap>
      <topx>54</topx>
      <topy>79</topy>
      <bottomx>56</bottomx>
      <bottomy>81</bottomy>
    </fire.pb.map.SWorldMapConfig>
  </entry>
  <entry>
    <int>1623</int>
    <fire.pb.map.SWorldMapConfig>
      <id>1623</id>
      <maptype>2</maptype>
      <LevelLimitMin>-1</LevelLimitMin>
      <LevelLimitMax>-1</LevelLimitMax>
      <SubUnderGroundMap>0</SubUnderGroundMap>
      <topx>53</topx>
      <topy>56</topy>
      <bottomx>55</bottomx>
      <bottomy>58</bottomy>
    </fire.pb.map.SWorldMapConfig>
  </entry>
  <entry>
    <int>1624</int>
    <fire.pb.map.SWorldMapConfig>
      <id>1624</id>
      <maptype>2</maptype>
      <LevelLimitMin>-1</LevelLimitMin>
      <LevelLimitMax>-1</LevelLimitMax>
      <SubUnderGroundMap>0</SubUnderGroundMap>
      <topx>15</topx>
      <topy>81</topy>
      <bottomx>17</bottomx>
      <bottomy>83</bottomy>
    </fire.pb.map.SWorldMapConfig>
  </entry>
  <entry>
    <int>1625</int>
    <fire.pb.map.SWorldMapConfig>
      <id>1625</id>
      <maptype>2</maptype>
      <LevelLimitMin>-1</LevelLimitMin>
      <LevelLimitMax>-1</LevelLimitMax>
      <SubUnderGroundMap>0</SubUnderGroundMap>
      <topx>31</topx>
      <topy>69</topy>
      <bottomx>33</bottomx>
      <bottomy>71</bottomy>
    </fire.pb.map.SWorldMapConfig>
  </entry>
  <entry>
    <int>1626</int>
    <fire.pb.map.SWorldMapConfig>
      <id>1626</id>
      <maptype>2</maptype>
      <LevelLimitMin>-1</LevelLimitMin>
      <LevelLimitMax>-1</LevelLimitMax>
      <SubUnderGroundMap>0</SubUnderGroundMap>
      <topx>13</topx>
      <topy>64</topy>
      <bottomx>15</bottomx>
      <bottomy>66</bottomy>
    </fire.pb.map.SWorldMapConfig>
  </entry>
  <entry>
    <int>1627</int>
    <fire.pb.map.SWorldMapConfig>
      <id>1627</id>
      <maptype>2</maptype>
      <LevelLimitMin>-1</LevelLimitMin>
      <LevelLimitMax>-1</LevelLimitMax>
      <SubUnderGroundMap>0</SubUnderGroundMap>
      <topx>49</topx>
      <topy>46</topy>
      <bottomx>51</bottomx>
      <bottomy>48</bottomy>
    </fire.pb.map.SWorldMapConfig>
  </entry>
  <entry>
    <int>1628</int>
    <fire.pb.map.SWorldMapConfig>
      <id>1628</id>
      <maptype>2</maptype>
      <LevelLimitMin>-1</LevelLimitMin>
      <LevelLimitMax>-1</LevelLimitMax>
      <SubUnderGroundMap>0</SubUnderGroundMap>
      <topx>20</topx>
      <topy>29</topy>
      <bottomx>22</bottomx>
      <bottomy>31</bottomy>
    </fire.pb.map.SWorldMapConfig>
  </entry>
  <entry>
    <int>1629</int>
    <fire.pb.map.SWorldMapConfig>
      <id>1629</id>
      <maptype>2</maptype>
      <LevelLimitMin>-1</LevelLimitMin>
      <LevelLimitMax>-1</LevelLimitMax>
      <SubUnderGroundMap>0</SubUnderGroundMap>
      <topx>43</topx>
      <topy>85</topy>
      <bottomx>45</bottomx>
      <bottomy>87</bottomy>
    </fire.pb.map.SWorldMapConfig>
  </entry>
  <entry>
    <int>1630</int>
    <fire.pb.map.SWorldMapConfig>
      <id>1630</id>
      <maptype>2</maptype>
      <LevelLimitMin>-1</LevelLimitMin>
      <LevelLimitMax>-1</LevelLimitMax>
      <SubUnderGroundMap>0</SubUnderGroundMap>
      <topx>119</topx>
      <topy>116</topy>
      <bottomx>121</bottomx>
      <bottomy>118</bottomy>
    </fire.pb.map.SWorldMapConfig>
  </entry>
  <entry>
    <int>1631</int>
    <fire.pb.map.SWorldMapConfig>
      <id>1631</id>
      <maptype>2</maptype>
      <LevelLimitMin>-1</LevelLimitMin>
      <LevelLimitMax>-1</LevelLimitMax>
      <SubUnderGroundMap>0</SubUnderGroundMap>
      <topx>30</topx>
      <topy>44</topy>
      <bottomx>32</bottomx>
      <bottomy>46</bottomy>
    </fire.pb.map.SWorldMapConfig>
  </entry>
  <entry>
    <int>1632</int>
    <fire.pb.map.SWorldMapConfig>
      <id>1632</id>
      <maptype>2</maptype>
      <LevelLimitMin>-1</LevelLimitMin>
      <LevelLimitMax>-1</LevelLimitMax>
      <SubUnderGroundMap>0</SubUnderGroundMap>
      <topx>34</topx>
      <topy>50</topy>
      <bottomx>36</bottomx>
      <bottomy>52</bottomy>
    </fire.pb.map.SWorldMapConfig>
  </entry>
  <entry>
    <int>9021</int>
    <fire.pb.map.SWorldMapConfig>
      <id>9021</id>
      <maptype>2</maptype>
      <LevelLimitMin>-1</LevelLimitMin>
      <LevelLimitMax>-1</LevelLimitMax>
      <SubUnderGroundMap>0</SubUnderGroundMap>
      <topx>126</topx>
      <topy>107</topy>
      <bottomx>128</bottomx>
      <bottomy>109</bottomy>
    </fire.pb.map.SWorldMapConfig>
  </entry>
  <entry>
    <int>5001</int>
    <fire.pb.map.SWorldMapConfig>
      <id>5001</id>
      <maptype>2</maptype>
      <LevelLimitMin>-1</LevelLimitMin>
      <LevelLimitMax>-1</LevelLimitMax>
      <SubUnderGroundMap>0</SubUnderGroundMap>
      <topx>57</topx>
      <topy>60</topy>
      <bottomx>59</bottomx>
      <bottomy>62</bottomy>
    </fire.pb.map.SWorldMapConfig>
  </entry>
  <entry>
    <int>5002</int>
    <fire.pb.map.SWorldMapConfig>
      <id>5002</id>
      <maptype>2</maptype>
      <LevelLimitMin>-1</LevelLimitMin>
      <LevelLimitMax>-1</LevelLimitMax>
      <SubUnderGroundMap>0</SubUnderGroundMap>
      <topx>57</topx>
      <topy>60</topy>
      <bottomx>59</bottomx>
      <bottomy>62</bottomy>
    </fire.pb.map.SWorldMapConfig>
  </entry>
  <entry>
    <int>5003</int>
    <fire.pb.map.SWorldMapConfig>
      <id>5003</id>
      <maptype>2</maptype>
      <LevelLimitMin>-1</LevelLimitMin>
      <LevelLimitMax>-1</LevelLimitMax>
      <SubUnderGroundMap>0</SubUnderGroundMap>
      <topx>57</topx>
      <topy>60</topy>
      <bottomx>59</bottomx>
      <bottomy>62</bottomy>
    </fire.pb.map.SWorldMapConfig>
  </entry>
  <entry>
    <int>5004</int>
    <fire.pb.map.SWorldMapConfig>
      <id>5004</id>
      <maptype>2</maptype>
      <LevelLimitMin>-1</LevelLimitMin>
      <LevelLimitMax>-1</LevelLimitMax>
      <SubUnderGroundMap>0</SubUnderGroundMap>
      <topx>57</topx>
      <topy>60</topy>
      <bottomx>59</bottomx>
      <bottomy>62</bottomy>
    </fire.pb.map.SWorldMapConfig>
  </entry>
  <entry>
    <int>5005</int>
    <fire.pb.map.SWorldMapConfig>
      <id>5005</id>
      <maptype>2</maptype>
      <LevelLimitMin>-1</LevelLimitMin>
      <LevelLimitMax>-1</LevelLimitMax>
      <SubUnderGroundMap>0</SubUnderGroundMap>
      <topx>57</topx>
      <topy>60</topy>
      <bottomx>59</bottomx>
      <bottomy>62</bottomy>
    </fire.pb.map.SWorldMapConfig>
  </entry>
  <entry>
    <int>5006</int>
    <fire.pb.map.SWorldMapConfig>
      <id>5006</id>
      <maptype>2</maptype>
      <LevelLimitMin>-1</LevelLimitMin>
      <LevelLimitMax>-1</LevelLimitMax>
      <SubUnderGroundMap>0</SubUnderGroundMap>
      <topx>57</topx>
      <topy>60</topy>
      <bottomx>59</bottomx>
      <bottomy>62</bottomy>
    </fire.pb.map.SWorldMapConfig>
  </entry>
  <entry>
    <int>5007</int>
    <fire.pb.map.SWorldMapConfig>
      <id>5007</id>
      <maptype>2</maptype>
      <LevelLimitMin>-1</LevelLimitMin>
      <LevelLimitMax>-1</LevelLimitMax>
      <SubUnderGroundMap>0</SubUnderGroundMap>
      <topx>57</topx>
      <topy>60</topy>
      <bottomx>59</bottomx>
      <bottomy>62</bottomy>
    </fire.pb.map.SWorldMapConfig>
  </entry>
  <entry>
    <int>5008</int>
    <fire.pb.map.SWorldMapConfig>
      <id>5008</id>
      <maptype>2</maptype>
      <LevelLimitMin>-1</LevelLimitMin>
      <LevelLimitMax>-1</LevelLimitMax>
      <SubUnderGroundMap>0</SubUnderGroundMap>
      <topx>57</topx>
      <topy>60</topy>
      <bottomx>59</bottomx>
      <bottomy>62</bottomy>
    </fire.pb.map.SWorldMapConfig>
  </entry>
  <entry>
    <int>5009</int>
    <fire.pb.map.SWorldMapConfig>
      <id>5009</id>
      <maptype>2</maptype>
      <LevelLimitMin>-1</LevelLimitMin>
      <LevelLimitMax>-1</LevelLimitMax>
      <SubUnderGroundMap>0</SubUnderGroundMap>
      <topx>57</topx>
      <topy>60</topy>
      <bottomx>59</bottomx>
      <bottomy>62</bottomy>
    </fire.pb.map.SWorldMapConfig>
  </entry>
  <entry>
    <int>5010</int>
    <fire.pb.map.SWorldMapConfig>
      <id>5010</id>
      <maptype>2</maptype>
      <LevelLimitMin>-1</LevelLimitMin>
      <LevelLimitMax>-1</LevelLimitMax>
      <SubUnderGroundMap>0</SubUnderGroundMap>
      <topx>57</topx>
      <topy>60</topy>
      <bottomx>59</bottomx>
      <bottomy>62</bottomy>
    </fire.pb.map.SWorldMapConfig>
  </entry>
  <entry>
    <int>5011</int>
    <fire.pb.map.SWorldMapConfig>
      <id>5011</id>
      <maptype>2</maptype>
      <LevelLimitMin>-1</LevelLimitMin>
      <LevelLimitMax>-1</LevelLimitMax>
      <SubUnderGroundMap>0</SubUnderGroundMap>
      <topx>57</topx>
      <topy>60</topy>
      <bottomx>59</bottomx>
      <bottomy>62</bottomy>
    </fire.pb.map.SWorldMapConfig>
  </entry>
  <entry>
    <int>5012</int>
    <fire.pb.map.SWorldMapConfig>
      <id>5012</id>
      <maptype>2</maptype>
      <LevelLimitMin>-1</LevelLimitMin>
      <LevelLimitMax>-1</LevelLimitMax>
      <SubUnderGroundMap>0</SubUnderGroundMap>
      <topx>57</topx>
      <topy>60</topy>
      <bottomx>59</bottomx>
      <bottomy>62</bottomy>
    </fire.pb.map.SWorldMapConfig>
  </entry>
  <entry>
    <int>5013</int>
    <fire.pb.map.SWorldMapConfig>
      <id>5013</id>
      <maptype>2</maptype>
      <LevelLimitMin>-1</LevelLimitMin>
      <LevelLimitMax>-1</LevelLimitMax>
      <SubUnderGroundMap>0</SubUnderGroundMap>
      <topx>57</topx>
      <topy>60</topy>
      <bottomx>59</bottomx>
      <bottomy>62</bottomy>
    </fire.pb.map.SWorldMapConfig>
  </entry>
  <entry>
    <int>5014</int>
    <fire.pb.map.SWorldMapConfig>
      <id>5014</id>
      <maptype>2</maptype>
      <LevelLimitMin>-1</LevelLimitMin>
      <LevelLimitMax>-1</LevelLimitMax>
      <SubUnderGroundMap>0</SubUnderGroundMap>
      <topx>57</topx>
      <topy>60</topy>
      <bottomx>59</bottomx>
      <bottomy>62</bottomy>
    </fire.pb.map.SWorldMapConfig>
  </entry>
  <entry>
    <int>5015</int>
    <fire.pb.map.SWorldMapConfig>
      <id>5015</id>
      <maptype>2</maptype>
      <LevelLimitMin>-1</LevelLimitMin>
      <LevelLimitMax>-1</LevelLimitMax>
      <SubUnderGroundMap>0</SubUnderGroundMap>
      <topx>57</topx>
      <topy>60</topy>
      <bottomx>59</bottomx>
      <bottomy>62</bottomy>
    </fire.pb.map.SWorldMapConfig>
  </entry>
  <entry>
    <int>5016</int>
    <fire.pb.map.SWorldMapConfig>
      <id>5016</id>
      <maptype>2</maptype>
      <LevelLimitMin>-1</LevelLimitMin>
      <LevelLimitMax>-1</LevelLimitMax>
      <SubUnderGroundMap>0</SubUnderGroundMap>
      <topx>57</topx>
      <topy>60</topy>
      <bottomx>59</bottomx>
      <bottomy>62</bottomy>
    </fire.pb.map.SWorldMapConfig>
  </entry>
  <entry>
    <int>5017</int>
    <fire.pb.map.SWorldMapConfig>
      <id>5017</id>
      <maptype>2</maptype>
      <LevelLimitMin>-1</LevelLimitMin>
      <LevelLimitMax>-1</LevelLimitMax>
      <SubUnderGroundMap>0</SubUnderGroundMap>
      <topx>57</topx>
      <topy>60</topy>
      <bottomx>59</bottomx>
      <bottomy>62</bottomy>
    </fire.pb.map.SWorldMapConfig>
  </entry>
  <entry>
    <int>5018</int>
    <fire.pb.map.SWorldMapConfig>
      <id>5018</id>
      <maptype>2</maptype>
      <LevelLimitMin>-1</LevelLimitMin>
      <LevelLimitMax>-1</LevelLimitMax>
      <SubUnderGroundMap>0</SubUnderGroundMap>
      <topx>57</topx>
      <topy>60</topy>
      <bottomx>59</bottomx>
      <bottomy>62</bottomy>
    </fire.pb.map.SWorldMapConfig>
  </entry>
  <entry>
    <int>5019</int>
    <fire.pb.map.SWorldMapConfig>
      <id>5019</id>
      <maptype>2</maptype>
      <LevelLimitMin>-1</LevelLimitMin>
      <LevelLimitMax>-1</LevelLimitMax>
      <SubUnderGroundMap>0</SubUnderGroundMap>
      <topx>57</topx>
      <topy>60</topy>
      <bottomx>59</bottomx>
      <bottomy>62</bottomy>
    </fire.pb.map.SWorldMapConfig>
  </entry>
  <entry>
    <int>5020</int>
    <fire.pb.map.SWorldMapConfig>
      <id>5020</id>
      <maptype>2</maptype>
      <LevelLimitMin>-1</LevelLimitMin>
      <LevelLimitMax>-1</LevelLimitMax>
      <SubUnderGroundMap>0</SubUnderGroundMap>
      <topx>57</topx>
      <topy>60</topy>
      <bottomx>59</bottomx>
      <bottomy>62</bottomy>
    </fire.pb.map.SWorldMapConfig>
  </entry>
  <entry>
    <int>8888</int>
    <fire.pb.map.SWorldMapConfig>
      <id>8888</id>
      <maptype>2</maptype>
      <LevelLimitMin>-1</LevelLimitMin>
      <LevelLimitMax>-1</LevelLimitMax>
      <SubUnderGroundMap>0</SubUnderGroundMap>
      <topx>40</topx>
      <topy>76</topy>
      <bottomx>40</bottomx>
      <bottomy>76</bottomy>
    </fire.pb.map.SWorldMapConfig>
  </entry>
  <entry>
    <int>6666</int>
    <fire.pb.map.SWorldMapConfig>
      <id>6666</id>
      <maptype>2</maptype>
      <LevelLimitMin>-1</LevelLimitMin>
      <LevelLimitMax>-1</LevelLimitMax>
      <SubUnderGroundMap>0</SubUnderGroundMap>
      <topx>12</topx>
      <topy>100</topy>
      <bottomx>12</bottomx>
      <bottomy>100</bottomy>
    </fire.pb.map.SWorldMapConfig>
  </entry>
</tree-map>