{
"skeleton": { "hash": "iGFoyNgJXWM2S+dtWodijz24Aqs", "spine": "2.1.27", "width": 552.04, "height": 444.13, "images": "./images/" },
"bones": [
	{ "name": "root" },
	{ "name": "sj1", "parent": "root", "length": 157.79, "x": 189.55, "y": -102.38, "rotation": 72.92 },
	{ "name": "sj2", "parent": "root", "length": 159.9, "x": -266.24, "y": -34.19, "rotation": 98.94 },
	{ "name": "sj3", "parent": "root", "length": 341.03, "x": -32.96, "y": -138.27, "rotation": 90.9 }
],
"slots": [
	{ "name": "sj2", "bone": "sj2", "attachment": "sj2" },
	{ "name": "sj1", "bone": "sj1", "attachment": "sj1" },
	{ "name": "sj3", "bone": "sj3", "attachment": "sj3" }
],
"skins": {
	"default": {
		"sj1": {
			"sj1": { "x": 32.03, "y": -4.23, "rotation": -72.92, "width": 80, "height": 204 }
		},
		"sj2": {
			"sj2": { "x": 32.33, "y": -4.83, "rotation": -98.94, "width": 85, "height": 225 }
		},
		"sj3": {
			"sj3": { "x": 101.11, "y": -10.57, "rotation": -90.9, "width": 340, "height": 444 }
		}
	}
},
"animations": {
	"play": {
		"bones": {
			"sj1": {
				"rotate": [
					{ "time": 0, "angle": 0, "curve": "stepped" },
					{ "time": 1.8666, "angle": 0 }
				],
				"translate": [
					{
						"time": 0,
						"x": 0,
						"y": 0,
						"curve": [ 0.25, 0, 0.75, 1 ]
					},
					{
						"time": 0.9333,
						"x": 0,
						"y": 15.03,
						"curve": [ 0.25, 0, 0.75, 1 ]
					},
					{ "time": 1.8666, "x": 0, "y": 0 }
				]
			},
			"sj2": {
				"rotate": [
					{ "time": 0, "angle": 0, "curve": "stepped" },
					{ "time": 1.8666, "angle": 0 }
				],
				"translate": [
					{
						"time": 0,
						"x": 0,
						"y": 3.9,
						"curve": [ 0.379, 0.6, 0.724, 1 ]
					},
					{
						"time": 0.2333,
						"x": 0,
						"y": 0,
						"curve": [ 0.25, 0, 0.75, 1 ]
					},
					{
						"time": 1.1666,
						"x": 0,
						"y": 21.14,
						"curve": [ 0.242, 0, 0.666, 0.66 ]
					},
					{ "time": 1.8666, "x": 0, "y": 3.9 }
				]
			},
			"sj3": {
				"rotate": [
					{ "time": 0, "angle": 0, "curve": "stepped" },
					{ "time": 0.4666, "angle": 0, "curve": "stepped" },
					{ "time": 1.8666, "angle": 0 }
				],
				"translate": [
					{
						"time": 0,
						"x": 0,
						"y": 4.52,
						"curve": [ 0.339, 0.51, 0.642, 1 ]
					},
					{
						"time": 0.4666,
						"x": 0,
						"y": 0,
						"curve": [ 0.387, 0, 0.622, 1 ]
					},
					{
						"time": 1.3666,
						"x": 0,
						"y": 9.04,
						"curve": [ 0.403, 0, 0.676, 0.48 ]
					},
					{ "time": 1.8666, "x": 0, "y": 4.52 }
				]
			}
		}
	}
}
}